cambridict/__init__.py
cambridict/cambridge.yaml
cambridict/const.py
cambridict/dictionary.py
cambridict-0.1.6.dist-info/LICENSE
cambridict-0.1.6.dist-info/METADATA
cambridict-0.1.6.dist-info/WHEEL
cambridict-0.1.6.dist-info/top_level.txt
cambridict-0.1.6.dist-info/RECORD
