Metadata-Version: 2.1
Name: cambridict
Version: 0.1.6
Summary: Search the meaning of the word from Cambridge Dictionary online, and get the result in JSON format
Home-page: https://github.com/tegieng7/cambridict
Author: Duy Nguyen
Author-email: tegieng7@gmail.com
License: MIT
Keywords: cambridge,dictionary
Platform: UNKNOWN
Classifier: License :: OSI Approved :: MIT License
Classifier: Operating System :: OS Independent
Requires-Dist: cssselect
Requires-Dist: lxml
Requires-Dist: requests
Requires-Dist: pyyaml
